tesla_dashcam/__init__.py
tesla_dashcam/__version__.py
tesla_dashcam/tesla_dashcam.py
tesla_dashcam-0.1.20.dist-info/AUTHORS
tesla_dashcam-0.1.20.dist-info/LICENSE
tesla_dashcam-0.1.20.dist-info/METADATA
tesla_dashcam-0.1.20.dist-info/WHEEL
tesla_dashcam-0.1.20.dist-info/entry_points.txt
tesla_dashcam-0.1.20.dist-info/top_level.txt
tesla_dashcam-0.1.20.dist-info/RECORD
