Metadata-Version: 2.1
Name: tesla-dashcam
Version: 0.1.20
Summary: Python program to merge video files created by Tesla dashcam
Home-page: https://github.com/ehendrix23/tesla_dashcam
Author: Erik Hendrix
License: Apache License 2.0
Platform: UNKNOWN
Classifier: Intended Audience :: End Users/Desktop
Classifier: License :: OSI Approved :: Apache Software License
Classifier: Programming Language :: Python
Classifier: Programming Language :: Python :: 3
Classifier: Programming Language :: Python :: 3.7
Classifier: Programming Language :: Python :: Implementation :: CPython
Classifier: Programming Language :: Python :: Implementation :: PyPy
Classifier: Topic :: Multimedia :: Video :: Conversion
Requires-Python: >=3.8.6
Requires-Dist: tzlocal
Requires-Dist: requests
Requires-Dist: psutil
Requires-Dist: python-dateutil
Requires-Dist: staticmap
